FPLI_Minimum_Commutes/__init__.py
FPLI_Minimum_Commutes/main.py
FPLI_Minimum_Commutes/minimum_commute_calculator.py
FPLI_Minimum_Commutes/old_implementation.py
FPLI_Minimum_Commutes/process_data.py
FPLI_Minimum_Commutes-11.dist-info/LICENSE
FPLI_Minimum_Commutes-11.dist-info/METADATA
FPLI_Minimum_Commutes-11.dist-info/WHEEL
FPLI_Minimum_Commutes-11.dist-info/top_level.txt
FPLI_Minimum_Commutes-11.dist-info/RECORD
