Metadata-Version: 2.1
Name: FPLI-Minimum-Commutes
Version: 11
Summary: FPLI Inter-District Minimum Commute Estimator
Home-page: https://github.com/kdewey13/CIS4914-Minimum_Commute_FPLI
Author: Kelsey Dewey
Author-email: fplimincomm@gmail.com
License: UNKNOWN
Platform: UNKNOWN
Classifier: Programming Language :: Python :: 3
Classifier: License :: OSI Approved :: MIT License
Classifier: Operating System :: OS Independent
Requires-Python: >=2.7
Requires-Dist: geopy
Requires-Dist: pandas
Requires-Dist: requests
Requires-Dist: pytz
Requires-Dist: tzlocal
Requires-Dist: openpyxl
Requires-Dist: xlsxwriter
